gishndev/__init__.py
gishndev/common.py
gishndev/gee_s2_funcs.py
gishndev/gishndev.py
gishndev-0.0.3.dist-info/LICENSE
gishndev-0.0.3.dist-info/METADATA
gishndev-0.0.3.dist-info/WHEEL
gishndev-0.0.3.dist-info/dependency_links.txt
gishndev-0.0.3.dist-info/top_level.txt
gishndev-0.0.3.dist-info/RECORD
