Metadata-Version: 2.2
Name: gishndev
Version: 0.0.3
Summary: A package to developed tools to processing gis data
Home-page: https://github.com/lalgonzales/gishndev
Author: Luis López
Author-email: lalgonzales@gmail.com
License: MIT license
Keywords: gishndev
Classifier: Intended Audience :: Developers
Classifier: License :: OSI Approved :: MIT License
Classifier: Natural Language :: English
Classifier: Programming Language :: Python :: 3
Classifier: Programming Language :: Python :: 3.8
Classifier: Programming Language :: Python :: 3.9
Classifier: Programming Language :: Python :: 3.10
Classifier: Programming Language :: Python :: 3.11
Requires-Python: >=3.8
License-File: LICENSE
Requires-Dist: geemap
Requires-Dist: leafmap
Requires-Dist: rasterio
Requires-Dist: shapely
Requires-Dist: geopandas
Requires-Dist: localtileserver
Requires-Dist: rioxarray
Dynamic: author
Dynamic: author-email
Dynamic: classifier
Dynamic: description
Dynamic: description-content-type
Dynamic: home-page
Dynamic: keywords
Dynamic: license
Dynamic: requires-dist
Dynamic: requires-python
Dynamic: summary
